{
	"index" : 1,
    "card": {
        "name": "Eruption",
        "effect": {
            "instants": [
				{
					"ieffect" : {
						"type": "DirectDamage",
						"element": "Fire",
						"params": {
							"amount": 10,
							"who": 0
						}
					},
					"icond" : {
						"type" : "AlwaysValid"
					}
				}
			],
            "persists": [
				{
					"type": "NoPersist"
				}
			],
            "triggers": [
				{
					"teffect" : {
						"type": "NoTrigger"
					},
					"tcond" : {
						"type" : "AlwaysValid"
					}
				}
			]
        }
    }
}
